fastapi_voyager/__init__.py
fastapi_voyager/cli.py
fastapi_voyager/er_diagram.py
fastapi_voyager/filter.py
fastapi_voyager/module.py
fastapi_voyager/pydantic_resolve_util.py
fastapi_voyager/render.py
fastapi_voyager/render_style.py
fastapi_voyager/server.py
fastapi_voyager/type.py
fastapi_voyager/type_helper.py
fastapi_voyager/version.py
fastapi_voyager/voyager.py
fastapi_voyager/adapters/__init__.py
fastapi_voyager/adapters/base.py
fastapi_voyager/adapters/common.py
fastapi_voyager/adapters/django_ninja_adapter.py
fastapi_voyager/adapters/fastapi_adapter.py
fastapi_voyager/adapters/litestar_adapter.py
fastapi_voyager/introspectors/__init__.py
fastapi_voyager/introspectors/base.py
fastapi_voyager/introspectors/detector.py
fastapi_voyager/introspectors/django_ninja.py
fastapi_voyager/introspectors/fastapi.py
fastapi_voyager/introspectors/litestar.py
fastapi_voyager/templates/dot/cluster.j2
fastapi_voyager/templates/dot/cluster_container.j2
fastapi_voyager/templates/dot/digraph.j2
fastapi_voyager/templates/dot/er_diagram.j2
fastapi_voyager/templates/dot/link.j2
fastapi_voyager/templates/dot/route_node.j2
fastapi_voyager/templates/dot/schema_node.j2
fastapi_voyager/templates/dot/tag_node.j2
fastapi_voyager/templates/html/colored_text.j2
fastapi_voyager/templates/html/pydantic_meta.j2
fastapi_voyager/templates/html/schema_field_row.j2
fastapi_voyager/templates/html/schema_header.j2
fastapi_voyager/templates/html/schema_table.j2
fastapi_voyager/web/graph-ui.js
fastapi_voyager/web/graphviz.svg.css
fastapi_voyager/web/graphviz.svg.js
fastapi_voyager/web/index.html
fastapi_voyager/web/quasar.min.css
fastapi_voyager/web/quasar.min.js
fastapi_voyager/web/store.js
fastapi_voyager/web/vue-main.js
fastapi_voyager/web/component/demo.js
fastapi_voyager/web/component/render-graph.js
fastapi_voyager/web/component/route-code-display.js
fastapi_voyager/web/component/schema-code-display.js
fastapi_voyager/web/icon/android-chrome-192x192.png
fastapi_voyager-0.16.1.dist-info/METADATA
fastapi_voyager-0.16.1.dist-info/WHEEL
fastapi_voyager-0.16.1.dist-info/entry_points.txt
fastapi_voyager-0.16.1.dist-info/licenses/LICENSE
fastapi_voyager-0.16.1.dist-info/RECORD
