Metadata-Version: 2.4
Name: fastapi-voyager
Version: 0.16.1
Summary: Visualize FastAPI application's routing tree and dependencies
Project-URL: Homepage, https://github.com/allmonday/fastapi-voyager
Project-URL: Source, https://github.com/allmonday/fastapi-voyager
Author-email: Tangkikodo <allmonday@126.com>
License: MIT
License-File: LICENSE
Keywords: fastapi,openapi,routing,visualization
Classifier: Framework :: FastAPI
Classifier: Intended Audience :: Developers
Classifier: License :: OSI Approved :: MIT License
Classifier: Programming Language :: Python :: 3
Classifier: Programming Language :: Python :: 3.10
Classifier: Programming Language :: Python :: 3.11
Classifier: Programming Language :: Python :: 3.12
Classifier: Programming Language :: Python :: 3.13
Classifier: Programming Language :: Python :: 3.14
Requires-Python: >=3.10
Requires-Dist: jinja2>=3.0.0
Requires-Dist: pydantic-resolve>=2.4.3
Provides-Extra: all
Requires-Dist: django-ninja>=1.5.3; extra == 'all'
Requires-Dist: django>=4.2; extra == 'all'
Requires-Dist: fastapi>=0.110; extra == 'all'
Requires-Dist: httpx; extra == 'all'
Requires-Dist: litestar>=2.19.0; extra == 'all'
Requires-Dist: pydantic>=2.0; extra == 'all'
Requires-Dist: pytest; extra == 'all'
Requires-Dist: pytest-asyncio; extra == 'all'
Requires-Dist: ruff; extra == 'all'
Requires-Dist: uvicorn; extra == 'all'
Provides-Extra: dev
Requires-Dist: httpx; extra == 'dev'
Requires-Dist: pytest; extra == 'dev'
Requires-Dist: pytest-asyncio; extra == 'dev'
Requires-Dist: ruff; extra == 'dev'
Provides-Extra: django-ninja
Requires-Dist: django-ninja>=1.5.3; extra == 'django-ninja'
Requires-Dist: django>=4.2; extra == 'django-ninja'
Requires-Dist: uvicorn; extra == 'django-ninja'
Provides-Extra: fastapi
Requires-Dist: fastapi>=0.110; extra == 'fastapi'
Requires-Dist: uvicorn; extra == 'fastapi'
Provides-Extra: litestar
Requires-Dist: litestar>=2.19.0; extra == 'litestar'
Requires-Dist: pydantic>=2.0; extra == 'litestar'
Requires-Dist: uvicorn; extra == 'litestar'
